taskiq_litestar/__init__.py
taskiq_litestar/intializer.py
taskiq_litestar-0.1.1.dist-info/LICENSE
taskiq_litestar-0.1.1.dist-info/METADATA
taskiq_litestar-0.1.1.dist-info/WHEEL
taskiq_litestar-0.1.1.dist-info/RECORD
